README.md
setup.cfg
setup.py
gmi_utils/__init__.py
gmi_utils/gmi_exception.py
gmi_utils/interval.py
gmiutilstest.egg-info/PKG-INFO
gmiutilstest.egg-info/SOURCES.txt
gmiutilstest.egg-info/dependency_links.txt
gmiutilstest.egg-info/top_level.txt